ovos_phal_plugin_aiy_v2/__init__.py
ovos_phal_plugin_aiy_v2/version.py
ovos_phal_plugin_aiy_v2-0.1.0.dist-info/LICENSE
ovos_phal_plugin_aiy_v2-0.1.0.dist-info/METADATA
ovos_phal_plugin_aiy_v2-0.1.0.dist-info/WHEEL
ovos_phal_plugin_aiy_v2-0.1.0.dist-info/entry_points.txt
ovos_phal_plugin_aiy_v2-0.1.0.dist-info/top_level.txt
ovos_phal_plugin_aiy_v2-0.1.0.dist-info/zip-safe
ovos_phal_plugin_aiy_v2-0.1.0.dist-info/RECORD
