Metadata-Version: 2.1
Name: ovos-phal-plugin-aiy-v2
Version: 0.1.0
Summary: A plugin to handle Google AIY Voice Kit V2 button and LED
Home-page: https://github.com/smartgic/ovos-phal-plugin-aiy-v2
Author: Gaëtan Trellu (goldyfruit)
Author-email: gaetan.trellu@gmail.com
License: Apache-2.0
Classifier: Development Status :: 3 - Alpha
Classifier: Intended Audience :: Developers
Classifier: Topic :: Text Processing :: Linguistic
Classifier: License :: OSI Approved :: Apache Software License
Classifier: Programming Language :: Python :: 3.9
Classifier: Programming Language :: Python :: 3.10
Classifier: Programming Language :: Python :: 3.11
Classifier: Programming Language :: Python :: 3.12
License-File: LICENSE
Requires-Dist: aiy-projects-python
Requires-Dist: json-database
Requires-Dist: ovos-bus-client
Requires-Dist: ovos-plugin-manager
